{"infeasibility_range":0.06,"P":[1.0],"labels":{"1.0":[[false,true,true,true,false,true,true,true,true,true,false,false,false,false,true,false,true,false,true,false,false,false,true,true,true,false,true,true,true,false,true,true,false,true,true,true,true,true,true,false,true,true,true,false,false,true,false,true,false,false]]},"EvalAve":-14.39218322456797,"elapsed_time":{"value":779869},"r":0.4,"objective_value":-14.509313215659382,"R":19,"optimal_solutions":[3.8768408959153384,7.088314881723875],"total_vol":186.91337018599165}