{"infeasibility_range":0.0,"P":[1.0],"labels":{"1.0":[[true,false,true,false,true,false,true,true,false,true,true,true,true,true,true,true,false,true,false,true,false,true,false,false,true,true,true,true,true,true,true,true,true,true,false,true,true,false,true,false,true,true,false,false,false,true,true,false,false,false]]},"EvalAve":-10.765275302935478,"elapsed_time":{"value":2007814},"r":0.35,"objective_value":-10.76527530293344,"R":12,"optimal_solutions":[4.253973589271322,4.340867809109433],"total_vol":388.1353911921796}