{"infeasibility_range":0.22,"P":[1.0],"labels":{"1.0":[[false,true,true,false,false,true,false,false,false,true,true,true,true,true,false,false,false,true,true,false,true,true,true,false,true,true,false,false,false,true,true,true,false,true,false,false,true,false,true,false,true,false,true,false,true,false,false,false,true,false]]},"EvalAve":-15.296058515529712,"elapsed_time":{"value":1188773},"r":0.5,"objective_value":-19.122570008645997,"R":10,"optimal_solutions":[11.849142544635829,4.848951644337401],"total_vol":162.62956778543423}