{"infeasibility_range":0.02,"P":[null],"labels":{"Inf":[[false,true,true,true,true,false,true,true,true,true,true,true,true,true,true,true,true,true,true,true,true,true,true,true,false,true,false,true,true,true,true,true,true,true,true,true,true,true,true,true,true,true,true,false,true,true,true,true,true,true]]},"EvalAve":-12.901777991585478,"elapsed_time":{"value":130108},"r":0.1,"objective_value":-13.081581893212714,"R":6,"optimal_solutions":[7.052704590118703,4.019251539054638],"total_vol":719.1192873796005}