{"infeasibility_range":0.16,"P":[1.0,null],"labels":{"Inf":[[false,false,false,false,false,false,false,true,false,false,false,false,false,false,true,false,false,false,false,true,false,false,false,true,false,false,false,false,false,false,false,false,true,false,true,false,false,false,false,false,false,false,false,false,true,false,false,false,true,false]],"1.0":[[true,false,true,true,true,false,false,false,false,true,false,true,false,false,false,true,false,true,false,false,false,false,true,false,true,true,false,false,false,false,true,false,false,false,false,true,false,false,true,true,true,false,true,true,false,true,false,false,false,true]]},"EvalAve":-18.556699411770243,"elapsed_time":{"value":5857681},"r":0.45,"objective_value":-19.050338393735302,"R":24,"optimal_solutions":[8.250422596241217,7.199943865544195],"total_vol":204.17559522236434}