{"infeasibility_range":0.06,"P":[1.0],"labels":{"1.0":[[false,false,false,false,true,false,false,true,false,true,true,true,true,false,true,true,false,false,false,false,false,false,true,true,true,true,false,false,false,true,false,true,true,false,true,true,true,true,false,false,true,true,true,false,false,true,true,false,true,false]]},"EvalAve":-15.066624870830665,"elapsed_time":{"value":1192586},"r":0.5,"objective_value":-15.773377263792714,"R":30,"optimal_solutions":[8.729870696996908,4.6956710450953745],"total_vol":171.42363157447562}