{"infeasibility_range":0.04,"P":[1.0,2.0],"labels":{"2.0":[[true,true,false,true,false,false,false,true,false,true,false,false,true,false,false,true,false,false,false,false,false,false,false,false,false,false,false,true,false,true,false,false,false,false,false,true,false,false,false,false,false,true,false,true,false,true,false,false,false,false]],"1.0":[[false,false,true,false,true,false,false,false,true,false,true,false,false,true,false,false,true,true,false,false,true,false,true,true,true,true,false,false,true,false,true,false,false,true,false,false,true,false,true,true,true,false,true,false,true,false,false,true,false,false]]},"EvalAve":-16.546977927156746,"elapsed_time":{"value":11189904},"r":0.3,"objective_value":-16.853753165500027,"R":15,"optimal_solutions":[7.8363901142622545,6.01157537261146],"total_vol":236.8037499690345}