{"infeasibility_range":0.02,"P":[null],"labels":{"Inf":[[true,true,true,true,true,false,true,false,true,true,false,true,true,false,false,true,true,false,true,true,true,false,true,false,true,true,false,false,true,true,true,true,false,false,true,true,true,false,false,true,true,true,false,true,true,false,false,true,false,true]]},"EvalAve":-10.959646531375602,"elapsed_time":{"value":596623},"r":0.35,"objective_value":-10.97757943887843,"R":11,"optimal_solutions":[3.2610432829768583,5.144357444363211],"total_vol":335.5096338199757}