{"infeasibility_range":0.44,"P":[null],"labels":{"Inf":[[true,true,false,true,false,false,true,true,false,true,false,false,true,true,true,true,true,true,false,false,true,false,true,true,false,true,true,true,true,true,false,false,false,true,false,true,true,false,false,true,false,true,true,true,true,true,false,true,false,false]]},"EvalAve":-21.57452173158699,"elapsed_time":{"value":1008295},"r":0.4,"objective_value":-28.731064117802056,"R":15,"optimal_solutions":[16.48521818350577,8.163897289950496],"total_vol":274.79888707909083}