{"infeasibility_range":0.1,"P":[1.0],"labels":{"1.0":[[true,true,false,true,false,false,false,true,false,true,false,false,true,true,false,true,false,true,false,true,false,false,true,true,false,true,false,true,false,true,false,true,false,true,false,true,true,false,false,false,false,true,true,true,true,true,false,true,false,false]]},"EvalAve":-15.458643784895685,"elapsed_time":{"value":1235233},"r":0.5,"objective_value":-16.285082636294412,"R":15,"optimal_solutions":[4.804242057896543,7.653893719476816],"total_vol":181.9101677993114}