{"infeasibility_range":0.14,"P":[1.0,2.0],"labels":{"2.0":[[false,false,true,true,true,true,false,true,false,false,true,false,true,false,true,true,true,true,false,false,false,true,false,false,true,true,true,false,false,false,false,false,true,true,true,false,true,false,true,false,false,true,true,true,true,false,true,false,false,true]],"1.0":[[false,false,false,false,false,false,true,false,false,true,false,true,false,false,false,false,false,false,false,true,false,false,false,true,false,false,false,false,true,false,false,false,false,false,false,false,false,false,false,false,false,false,false,false,false,false,false,false,false,false]]},"EvalAve":-18.020038281694763,"elapsed_time":{"value":27589601},"r":0.35,"objective_value":-18.72143355148868,"R":20,"optimal_solutions":[6.886008056583156,7.890283663779494],"total_vol":199.1342596323029}