{"infeasibility_range":0.14,"P":[1.0],"labels":{"1.0":[[true,true,false,false,true,true,false,false,false,false,true,false,false,true,true,true,true,true,true,true,false,true,false,false,true,false,false,true,true,true,false,false,false,true,true,false,true,false,true,false,false,true,true,true,false,false,false,false,true,false]]},"EvalAve":-18.38913453510183,"elapsed_time":{"value":1194809},"r":0.5,"objective_value":-19.568315852402776,"R":13,"optimal_solutions":[7.549192873918873,8.012748652360845],"total_vol":152.65729625093692}