{"infeasibility_range":0.12,"P":[1.0,null],"labels":{"Inf":[[false,false,false,true,false,false,false,true,true,false,false,false,false,false,false,false,false,false,true,false,false,false,false,false,false,false,false,false,false,false,false,false,false,false,true,false,true,false,true,false,false,false,true,false,false,false,false,false,false,false]],"1.0":[[false,true,true,false,false,true,true,false,false,true,false,false,false,false,true,false,true,false,false,false,false,false,true,true,true,false,true,true,true,false,true,true,false,true,false,true,false,true,false,false,true,true,false,false,false,true,false,true,false,false]]},"EvalAve":-19.558545333207295,"elapsed_time":{"value":58919},"r":0.4,"objective_value":-20.285904992016917,"R":19,"optimal_solutions":[9.162792683142786,7.4154082059453925],"total_vol":155.72307197035389}