{"infeasibility_range":0.54,"P":[null],"labels":{"Inf":[[false,false,false,false,true,true,true,false,false,true,false,true,true,false,false,true,true,false,true,true,false,true,true,false,false,false,false,true,false,false,true,true,true,true,true,false,false,false,false,true,true,true,false,false,true,false,true,true,true,false]]},"EvalAve":-21.470232246127594,"elapsed_time":{"value":41528},"r":0.5,"objective_value":-32.867653114007396,"R":3,"optimal_solutions":[11.724558412289456,14.0953964678204],"total_vol":118.75714530036424}