{"infeasibility_range":0.02,"P":[1.0],"labels":{"1.0":[[true,true,false,true,true,false,false,true,false,true,true,false,true,true,false,true,true,true,false,true,true,false,true,true,false,true,false,true,true,true,true,true,false,true,false,true,true,false,false,true,false,true,true,true,true,true,false,true,false,false]]},"EvalAve":-9.097881038614538,"elapsed_time":{"value":53334},"r":0.35,"objective_value":-1.376406410780092,"R":15,"optimal_solutions":[3.6572978912672305e-13,6.187152379979134],"total_vol":343.9376507812991}