{"infeasibility_range":0.2,"P":[1.0],"labels":{"1.0":[[true,true,false,false,true,false,false,true,false,true,true,false,true,true,false,true,false,false,false,true,true,true,true,true,true,true,false,true,true,false,true,false,false,false,false,false,true,false,false,false,false,false,true,true,true,false,false,true,true,false]]},"EvalAve":-17.53746300004396,"elapsed_time":{"value":46538},"r":0.5,"objective_value":-20.075800463095415,"R":7,"optimal_solutions":[11.543180725745891,5.6884131593070215],"total_vol":203.60750070749955}