{"infeasibility_range":0.04,"P":[1.0,2.0],"labels":{"2.0":[[false,false,true,false,false,false,true,false,false,false,false,false,false,true,false,true,false,false,true,false,false,false,false,false,false,false,false,false,false,false,false,false,false,false,false,false,false,false,false,true,false,false,false,false,false,false,false,false,false,false]],"1.0":[[false,false,false,false,true,false,false,true,true,false,false,true,true,false,true,false,false,false,false,true,false,false,false,false,true,false,false,true,false,true,false,false,true,false,true,true,true,true,false,false,true,false,false,true,false,true,false,false,true,false]]},"EvalAve":-15.502333354817257,"elapsed_time":{"value":39135},"r":0.5,"objective_value":-15.712940806954116,"R":30,"optimal_solutions":[7.036432999527861,5.784338538286316],"total_vol":305.29043228336513}