{"infeasibility_range":0.0,"P":[1.0],"labels":{"1.0":[[true,true,true,true,true,true,true,true,true,true,true,true,true,true,true,true,true,true,true,true,true,true,true,true,true,false,true,true,true,true,false,true,true,true,true,false,true,false,false,true,true,true,false,false,true,true,true,true,false,true]]},"EvalAve":-13.64616967405048,"elapsed_time":{"value":48404},"r":0.15,"objective_value":15.786469888527392,"R":26,"optimal_solutions":[1.6920335917092875e-11,9.614754882686311],"total_vol":524.3670657675499}