{"infeasibility_range":0.02,"P":[2.0,null],"labels":{"2.0":[[true,false,true,true,true,true,true,true,true,true,false,false,true,true,true,true,false,true,false,false,true,true,false,false,true,false,true,true,true,false,true,false,true,true,true,true,false,false,false,false,false,true,true,false,false,true,true,false,true,true]],"Inf":[[false,false,false,false,false,false,false,false,false,false,true,true,false,false,false,false,true,false,true,true,false,false,true,false,false,true,false,false,false,true,false,true,false,false,false,false,true,true,true,true,true,false,false,true,true,false,false,true,false,false]]},"EvalAve":-10.588767942913728,"elapsed_time":{"value":90563},"r":0.05,"objective_value":-10.612209834901105,"R":23,"optimal_solutions":[2.8056051582593016,5.204403118294528],"total_vol":688.3530132698711}