{"infeasibility_range":0.0,"P":[null],"labels":{"Inf":[[true,true,true,true,true,true,true,true,true,true,true,true,true,true,true,true,true,true,true,true,false,true,false,true,true,true,true,true,true,true,true,true,true,true,true,true,true,true,true,true,true,true,true,true,true,true,true,true,true,true]]},"EvalAve":-1.7291807560656642,"elapsed_time":{"value":51431},"r":0.05,"objective_value":4.652996220188051,"R":9,"optimal_solutions":[1.7291807558669992,1.324437773245572e-10],"total_vol":1030.162199004579}