{"infeasibility_range":0.0,"P":[1.0,2.0],"labels":{"2.0":[[true,true,true,false,true,false,false,false,false,true,false,false,false,true,false,true,false,false,true,false,true,false,false,false,true,false,true,true,false,false,false,true,false,false,false,true,false,false,true,true,false,false,true,true,true,false,false,true,true,false]],"1.0":[[false,false,false,true,false,true,true,true,true,false,true,true,true,false,true,false,true,true,false,true,false,true,true,true,false,true,false,false,true,true,false,false,false,true,true,false,false,true,false,false,true,true,false,false,false,true,true,false,false,true]]},"EvalAve":-5.359375916914073,"elapsed_time":{"value":80784},"r":0.05,"objective_value":-5.359375916679464,"R":1,"optimal_solutions":[3.807089901904815,1.0348573433394999],"total_vol":608.7355787937845}