{"infeasibility_range":0.02,"P":[null],"labels":{"Inf":[[false,true,true,false,true,false,true,true,true,true,true,false,true,false,true,true,true,true,true,true,true,true,true,true,true,true,true,true,true,true,true,true,true,true,false,true,true,true,true,true,false,true,true,true,false,true,true,true,true,true]]},"EvalAve":-14.133507880230152,"elapsed_time":{"value":51683},"r":0.15,"objective_value":-14.426083709052175,"R":6,"optimal_solutions":[8.180423813283344,4.163773264252303],"total_vol":552.3576096184195}