{"infeasibility_range":0.16,"P":[2.0],"labels":{"2.0":[[false,false,false,true,false,true,true,true,true,false,true,true,true,false,true,false,true,true,false,true,false,true,true,true,false,true,false,false,false,true,false,false,false,true,true,false,false,true,false,false,true,true,false,false,false,true,true,false,false,true]]},"EvalAve":-18.53279259156109,"elapsed_time":{"value":41317},"r":0.5,"objective_value":-19.82216102710027,"R":1,"optimal_solutions":[5.128057881376013,9.796068838803684],"total_vol":247.08836595657857}