{"infeasibility_range":0.22,"P":[2.0,null],"labels":{"2.0":[[false,false,true,false,false,false,true,false,false,true,false,false,false,false,false,false,false,false,false,true,false,false,false,true,false,false,false,false,true,false,false,false,false,true,false,true,false,false,false,false,false,false,false,false,false,false,true,false,false,false]],"Inf":[[true,false,false,true,true,true,false,true,false,false,true,false,true,false,true,true,true,true,false,false,false,true,false,false,true,true,false,false,false,false,false,false,true,false,true,false,true,false,false,false,true,true,true,true,true,false,false,false,false,true]]},"EvalAve":-16.36400396415976,"elapsed_time":{"value":57534},"r":0.35,"objective_value":-19.467370562553633,"R":20,"optimal_solutions":[3.9476124617649613,10.346505427814414],"total_vol":176.41580484021435}