{"infeasibility_range":0.04,"P":[null],"labels":{"Inf":[[true,true,false,true,true,false,true,true,false,true,true,true,true,true,true,true,false,true,true,true,true,true,true,true,true,true,true,true,false,false,true,false,false,true,true,false,true,true,true,true,false,true,true,true,true,true,false,true,true,false]]},"EvalAve":-14.560083497803092,"elapsed_time":{"value":51136},"r":0.25,"objective_value":-14.619981219087272,"R":7,"optimal_solutions":[4.338010604843281,6.854647076359747],"total_vol":433.63242027802323}